AUTHORS.rst
HISTORY.rst
LICENSE
MANIFEST.in
README.rst
acapela.py
setup.py
docs/Makefile
docs/make.bat
docs/source/conf.py
docs/source/index.rst
docs/source/installation-overview.rst
docs/source/introduction.rst
docs/source/resources.rst
python_acapela.egg-info/PKG-INFO
python_acapela.egg-info/SOURCES.txt
python_acapela.egg-info/dependency_links.txt
python_acapela.egg-info/entry_points.txt
python_acapela.egg-info/namespace_packages.txt
python_acapela.egg-info/not-zip-safe
python_acapela.egg-info/top_level.txt