Metadata-Version: 1.1
Name: python-acapela
Version: 0.2.6
Summary: Python Acapela Text-To-Speech
Home-page: http://github.com/areski/python-acapela
Author: Arezqui Belaid
Author-email: areski@gmail.com
License: MIT license
Keywords: tts,speech,text-to-speech,acapela
Platform: UNKNOWN
Classifier: Development Status :: 5 - Production/Stable
Classifier: Environment :: Console
Classifier: Intended Audience :: Developers
Classifier: License :: OSI Approved :: MIT License
Classifier: Operating System :: OS Independent
Classifier: Programming Language :: Python :: 2
Classifier: Programming Language :: Python :: 2.7
Classifier: Programming Language :: Python :: 3
Classifier: Programming Language :: Python :: 3.3
Classifier: Programming Language :: Python :: 3.4
Classifier: Topic :: Multimedia :: Sound/Audio :: Speech
Classifier: Topic :: Software Development :: Libraries :: Python Modules
